epcis_event_hash_generator/14b10c9d3e92d35f577bfc610fe5ec15aa2941124987919389d7cd9998516861.jsonld
epcis_event_hash_generator/__init__.py
epcis_event_hash_generator/__main__.py
epcis_event_hash_generator/context.py
epcis_event_hash_generator/dl_normaliser.py
epcis_event_hash_generator/e532647e8eb371379b8b0e8602d8981c8566bc60f7351f22c76a5bc865962008.jsonld
epcis_event_hash_generator/events_from_file_reader.py
epcis_event_hash_generator/file_document_loader.py
epcis_event_hash_generator/hash_generator.py
epcis_event_hash_generator/json_to_py.py
epcis_event_hash_generator/json_xml_model_mismatch_correction.py
epcis_event_hash_generator/xml_to_py.py
epcis_event_hash_generator-1.9.3.dist-info/LICENSE
epcis_event_hash_generator-1.9.3.dist-info/METADATA
epcis_event_hash_generator-1.9.3.dist-info/WHEEL
epcis_event_hash_generator-1.9.3.dist-info/entry_points.txt
epcis_event_hash_generator-1.9.3.dist-info/top_level.txt
epcis_event_hash_generator-1.9.3.dist-info/RECORD
