Metadata-Version: 2.1
Name: epcis-event-hash-generator
Version: 1.9.3
Summary: Exemplary implementation of the EPCIS event hash generator algorithm described in the README
Home-page: https://github.com/RalphTro/epcis-event-hash-generator
Author: Package author: Sebastian Schmittner
Author-email: sebastian.schmittner@eecc.de
License: MIT
Keywords: epcis GS1 hashing traceability
Classifier: Programming Language :: Python :: 3
Classifier: Programming Language :: Python :: 3.8
Classifier: License :: OSI Approved :: MIT License
Classifier: Operating System :: OS Independent
Requires-Python: >=3.6
License-File: LICENSE
Requires-Dist: python-dateutil (>=2.8)
Requires-Dist: Flask (>=1.1)
Requires-Dist: PyLD (>=2.0.3)
